harpiawatch/__init__.py
harpiawatch/config.py
harpiawatch/core.py
harpiawatch/utils.py
tests/__init__.py
harpiawatchforest-1.0.0.dist-info/LICENSE.txt
harpiawatchforest-1.0.0.dist-info/METADATA
harpiawatchforest-1.0.0.dist-info/WHEEL
harpiawatchforest-1.0.0.dist-info/top_level.txt
harpiawatchforest-1.0.0.dist-info/RECORD
