Metadata-Version: 2.1
Name: harpiawatchforest
Version: 1.0.0
Summary: Sistema de detección de pérdida de cobertura vegetal mediante Google Earth Engine
Home-page: 
Author: Elvis Garcia, Yubrany Gonzalez
Author-email: 
Maintainer: Ministerio de Ambiente de Panamá
License: MIT
Project-URL: Homepage, https://github.com/elvisgarcia/HarpiaWatchForest
Project-URL: Repository, https://github.com/elvisgarcia/HarpiaWatchForest
Project-URL: Issues, https://github.com/elvisgarcia/HarpiaWatchForest/issues
Keywords: google-earth-engine,remote-sensing,deforestation,forest-monitoring,vegetation-loss
Classifier: Development Status :: 5 - Production/Stable
Classifier: Intended Audience :: Science/Research
Classifier: Topic :: Scientific/Engineering :: GIS
Classifier: License :: OSI Approved :: MIT License
Classifier: Programming Language :: Python :: 3
Requires-Python: >=3.7
License-File: LICENSE.txt
Requires-Dist: earthengine-api >=0.1.350
